dcurves/__init__.py
dcurves/dca.py
dcurves/plot_graphs.py
dcurves/prevalence.py
dcurves/risks.py
dcurves/data/df_binary.csv
dcurves/data/df_case_control.csv
dcurves/data/df_surv.csv
public/simple_binary_dca.png
dcurves-1.1.7.dist-info/METADATA
dcurves-1.1.7.dist-info/WHEEL
dcurves-1.1.7.dist-info/licenses/LICENSE
dcurves-1.1.7.dist-info/RECORD
