Metadata-Version: 2.4
Name: dcurves
Version: 1.1.7
Summary: A Python package for Decision Curve Analysis to evaluate prediction models, molecular markers, and diagnostic tests.
Project-URL: homepage, https://decisioncurveanalysis.org
Project-URL: repository, https://github.com/MSKCC-Epi-Bio/dcurves
Project-URL: documentation, https://github.com/MSKCC-Epi-Bio/dcurves/blob/main/docs/CHANGELOG.md
Author-email: Shaun Porwal <shaun.porwal@gmail.com>, Rohan Singh <singhrohan@outlook.com>
Maintainer-email: Shaun Porwal <shaun.porwal@gmail.com>
License: Apache-2.0
License-File: LICENSE
Keywords: andrew-vickers,clinical,consequences,decision-curve-analysis,decision-curves,net-benefit,rohan-singh,shaun-porwal
Classifier: Development Status :: 4 - Beta
Classifier: Intended Audience :: Science/Research
Classifier: License :: OSI Approved :: Apache Software License
Classifier: Programming Language :: Python :: 3.9
Classifier: Programming Language :: Python :: 3.10
Classifier: Programming Language :: Python :: 3.11
Classifier: Programming Language :: Python :: 3.12
Classifier: Programming Language :: Python :: 3.13
Classifier: Topic :: Software Development :: Libraries :: Python Modules
Requires-Python: <3.14,>=3.9
Requires-Dist: lifelines>=0.27.8
Requires-Dist: matplotlib>=3.7.1
Requires-Dist: pandas>=2.2.3
Requires-Dist: statsmodels>=0.14.5
Provides-Extra: dev
Requires-Dist: autopep8>=2.3.1; extra == 'dev'
Requires-Dist: black>=24.10.0; extra == 'dev'
Requires-Dist: jupyterlab~=3.6.1; extra == 'dev'
Requires-Dist: pylint>=3.3.1; extra == 'dev'
Requires-Dist: pytest-cov>=4.0.0; extra == 'dev'
Requires-Dist: pytest-mock>=3.14.0; extra == 'dev'
Requires-Dist: pytest>=7.2.2; extra == 'dev'
Requires-Dist: scikit-learn>=1.6.1; extra == 'dev'
Requires-Dist: tomli>=2.0.1; extra == 'dev'
Requires-Dist: tox>=4.4.6; extra == 'dev'
